upackage/__init__.py
upackage/__main__.py
upackage/metafile_template.yaml
upackage/upackage.py
upackage-0.3.4.dist-info/LICENSE
upackage-0.3.4.dist-info/METADATA
upackage-0.3.4.dist-info/WHEEL
upackage-0.3.4.dist-info/entry_points.txt
upackage-0.3.4.dist-info/top_level.txt
upackage-0.3.4.dist-info/RECORD
