Metadata-Version: 2.1
Name: upackage
Version: 0.3.4
Summary: Generate .unitypackage without Unity.
Home-page: https://github.com/AgeOfLearning/upackage
Author: Age of Learning
Author-email: leonid.umanskiy@aofl.com
License: MIT
Keywords: upackage
Platform: UNKNOWN
Classifier: Development Status :: 2 - Pre-Alpha
Classifier: Intended Audience :: Developers
Classifier: License :: OSI Approved :: MIT License
Classifier: Natural Language :: English
Classifier: Programming Language :: Python :: 2
Classifier: Programming Language :: Python :: 2.7
Classifier: Programming Language :: Python :: 3
Classifier: Programming Language :: Python :: 3.4
Classifier: Programming Language :: Python :: 3.5
Classifier: Programming Language :: Python :: 3.6
Classifier: Programming Language :: Python :: 3.7
License-File: LICENSE
Requires-Dist: PyYAML
Requires-Dist: pytest
